emmet/__init__.py
emmet/submissions.py
emmet/abinit/__init__.py
emmet/abinit/phonon.py
emmet/borg/icsd_to_mongo.py
emmet/common/__init__.py
emmet/common/aggregate.py
emmet/common/copybuilder.py
emmet/common/utils.py
emmet/common/tests/__init__.py
emmet/common/tests/test_copybuilder.py
emmet/materials/__init__.py
emmet/materials/boltztrap.py
emmet/materials/bonds.py
emmet/materials/dielectric.py
emmet/materials/diffraction.py
emmet/materials/electrodes.py
emmet/materials/magnetism.py
emmet/materials/mp_website.py
emmet/materials/property_workflows.py
emmet/materials/site_descriptors.py
emmet/materials/snls.py
emmet/materials/structure_prediction.py
emmet/materials/structure_similarity.py
emmet/materials/substrates.py
emmet/materials/thermo.py
emmet/materials/xas.py
emmet/materials/settings/__init__.py
emmet/materials/settings/substrates.yaml
emmet/materials/settings/xrd.json
emmet/materials/tests/__init__.py
emmet/materials/tests/test_diffraction.py
emmet/materials/tests/test_property_workflows.py
emmet/materials/tests/test_site_descriptors.py
emmet/materials/tests/test_structure_similarity.py
emmet/materials/tests/test_thermo.py
emmet/plotting/__init__.py
emmet/plotting/electronic_structure.py
emmet/plotting/phonon.py
emmet/plotting/tests/test_electronic_structure.py
emmet/tests/test_submissions.py
emmet/vasp/__init__.py
emmet/vasp/elastic.py
emmet/vasp/materials.py
emmet/vasp/ml_structures.py
emmet/vasp/mpworks.py
emmet/vasp/task_tagger.py
emmet/vasp/topology.py
emmet/vasp/topology_summary.py
emmet/vasp/builders/__init__.py
emmet/vasp/builders/task_tagger.py
emmet/vasp/settings/__init__.py
emmet/vasp/settings/materials_settings.json
emmet/vasp/settings/mpworks_conversion.yaml
emmet/vasp/tests/test_elastic.py
emmet/vasp/tests/test_materials.py
emmet/vasp/tests/test_ml_structure.py
emmet/vasp/tests/test_mpworks.py
emmet/vasp/tests/test_task_tagger.py
emmet-2018.6.7.dist-info/DESCRIPTION.rst
emmet-2018.6.7.dist-info/METADATA
emmet-2018.6.7.dist-info/RECORD
emmet-2018.6.7.dist-info/WHEEL
emmet-2018.6.7.dist-info/metadata.json
emmet-2018.6.7.dist-info/top_level.txt
