Metadata-Version: 2.0
Name: emmet
Version: 2018.6.7
Summary: Emmet is a builder framework for the Materials Project
Home-page: https://github.com/materialsproject/emmet
Author: MP team
Author-email: matproj-develop@googlegroups.com
License: modified BSD
Platform: UNKNOWN
Classifier: Programming Language :: Python :: 3
Classifier: Programming Language :: Python :: 3.6
Classifier: Development Status :: 2 - Pre-Alpha
Classifier: Intended Audience :: Science/Research
Classifier: Intended Audience :: System Administrators
Classifier: Intended Audience :: Information Technology
Classifier: Operating System :: OS Independent
Classifier: Topic :: Other/Nonlisted Topic
Classifier: Topic :: Scientific/Engineering
Requires-Python: >=3.6
Requires-Dist: atomate
Requires-Dist: maggma
Requires-Dist: matminer
Requires-Dist: monty
Requires-Dist: networkx
Requires-Dist: prettyplotlib
Requires-Dist: pybtex
Requires-Dist: pydash
Requires-Dist: pymatgen (>=2018.4.20)
Requires-Dist: six
Requires-Dist: sumo
Requires-Dist: tqdm
